<?xml version="1.0" encoding="UTF-8"?>

<!-- generated on 2023-09-19 11:45:20 by Eclipse SUMO sumo Version 1.18.0
<configuration xmlns:xsi="http://www.w3.org/2001/XMLSchema-instance" xsi:noNamespaceSchemaLocation="http://sumo.dlr.de/xsd/sumoConfiguration.xsd">

    <input>
        <net-file value="./nets/cologne8/cologne8.net.xml"/>
        <route-files value="./nets/cologne8/cologne8.rou.xml"/>
        <additional-files value="./nets/cologne8/cologne8.add.xml"/>
    </input>

    <processing>
        <time-to-teleport value="-1"/>
        <waiting-time-memory value="1000"/>
        <max-depart-delay value="-1"/>
    </processing>

    <traci_server>
        <remote-port value="50477"/>
    </traci_server>

    <random_number>
        <random value="true"/>
    </random_number>

</configuration>
-->

<detector xmlns:xsi="http://www.w3.org/2001/XMLSchema-instance" xsi:noNamespaceSchemaLocation="http://sumo.dlr.de/xsd/det_e2_file.xsd">
   <interval begin="0.00" end="300.00" id="e2_8" sampledSeconds="1.91" nVehEntered="1" nVehLeft="1" nVehSeen="1" meanSpeed="12.72" meanTimeLoss="0.09" meanOccupancy="0.13" maxOccupancy="21.50" meanMaxJamLengthInVehicles="0.00" meanMaxJamLengthInMeters="0.00" maxJamLengthInVehicles="0" maxJamLengthInMeters="0.00" jamLengthInVehiclesSum="0" jamLengthInMetersSum="0.00" meanHaltingDuration="0.00" maxHaltingDuration="0.00" haltingDurationSum="0.00" meanIntervalHaltingDuration="0.00" maxIntervalHaltingDuration="0.00" intervalHaltingDurationSum="0.00" startedHalts="0.00" meanVehicleNumber="0.01" maxVehicleNumber="1" />
   <interval begin="300.00" end="600.00" id="e2_8" sampledSeconds="0.00" nVehEntered="0" nVehLeft="0" nVehSeen="0" meanSpeed="-1.00" meanTimeLoss="-1.00" meanOccupancy="0.00" maxOccupancy="0.00" meanMaxJamLengthInVehicles="0.00" meanMaxJamLengthInMeters="0.00" maxJamLengthInVehicles="0" maxJamLengthInMeters="0.00" jamLengthInVehiclesSum="0" jamLengthInMetersSum="0.00" meanHaltingDuration="0.00" maxHaltingDuration="0.00" haltingDurationSum="0.00" meanIntervalHaltingDuration="0.00" maxIntervalHaltingDuration="0.00" intervalHaltingDurationSum="0.00" startedHalts="0.00" meanVehicleNumber="0.00" maxVehicleNumber="0" />
   <interval begin="600.00" end="900.00" id="e2_8" sampledSeconds="60.87" nVehEntered="6" nVehLeft="4" nVehSeen="6" meanSpeed="1.66" meanTimeLoss="8.91" meanOccupancy="4.38" maxOccupancy="46.94" meanMaxJamLengthInVehicles="0.13" meanMaxJamLengthInMeters="0.62" maxJamLengthInVehicles="2" maxJamLengthInMeters="10.28" jamLengthInVehiclesSum="39" jamLengthInMetersSum="184.67" meanHaltingDuration="10.50" maxHaltingDuration="19.00" haltingDurationSum="42.00" meanIntervalHaltingDuration="10.50" maxIntervalHaltingDuration="19.00" intervalHaltingDurationSum="42.00" startedHalts="5.00" meanVehicleNumber="0.22" maxVehicleNumber="3" />
   <interval begin="900.00" end="1200.00" id="e2_8" sampledSeconds="155.99" nVehEntered="13" nVehLeft="15" nVehSeen="15" meanSpeed="1.88" meanTimeLoss="8.95" meanOccupancy="10.64" maxOccupancy="64.50" meanMaxJamLengthInVehicles="0.34" meanMaxJamLengthInMeters="1.64" maxJamLengthInVehicles="3" maxJamLengthInMeters="15.97" jamLengthInVehiclesSum="101" jamLengthInMetersSum="492.93" meanHaltingDuration="15.25" maxHaltingDuration="24.00" haltingDurationSum="122.00" meanIntervalHaltingDuration="13.25" maxIntervalHaltingDuration="24.00" intervalHaltingDurationSum="106.00" startedHalts="7.00" meanVehicleNumber="0.56" maxVehicleNumber="3" />
   <interval begin="1200.00" end="1500.00" id="e2_8" sampledSeconds="6.66" nVehEntered="3" nVehLeft="3" nVehSeen="3" meanSpeed="9.74" meanTimeLoss="0.67" meanOccupancy="0.48" maxOccupancy="21.50" meanMaxJamLengthInVehicles="0.00" meanMaxJamLengthInMeters="0.00" maxJamLengthInVehicles="0" maxJamLengthInMeters="0.00" jamLengthInVehiclesSum="0" jamLengthInMetersSum="0.00" meanHaltingDuration="0.00" maxHaltingDuration="0.00" haltingDurationSum="0.00" meanIntervalHaltingDuration="0.00" maxIntervalHaltingDuration="0.00" intervalHaltingDurationSum="0.00" startedHalts="0.00" meanVehicleNumber="0.03" maxVehicleNumber="1" />
   <interval begin="1500.00" end="1800.00" id="e2_8" sampledSeconds="28.47" nVehEntered="6" nVehLeft="6" nVehSeen="6" meanSpeed="4.74" meanTimeLoss="3.06" meanOccupancy="1.81" maxOccupancy="21.50" meanMaxJamLengthInVehicles="0.03" meanMaxJamLengthInMeters="0.12" maxJamLengthInVehicles="1" maxJamLengthInMeters="4.11" jamLengthInVehiclesSum="9" jamLengthInMetersSum="34.67" meanHaltingDuration="10.00" maxHaltingDuration="10.00" haltingDurationSum="10.00" meanIntervalHaltingDuration="10.00" maxIntervalHaltingDuration="10.00" intervalHaltingDurationSum="10.00" startedHalts="2.00" meanVehicleNumber="0.11" maxVehicleNumber="1" />
   <interval begin="1800.00" end="2100.00" id="e2_8" sampledSeconds="15.90" nVehEntered="1" nVehLeft="1" nVehSeen="1" meanSpeed="1.53" meanTimeLoss="14.35" meanOccupancy="1.11" maxOccupancy="21.50" meanMaxJamLengthInVehicles="0.04" meanMaxJamLengthInMeters="0.16" maxJamLengthInVehicles="1" maxJamLengthInMeters="4.30" jamLengthInVehiclesSum="11" jamLengthInMetersSum="47.30" meanHaltingDuration="12.00" maxHaltingDuration="12.00" haltingDurationSum="12.00" meanIntervalHaltingDuration="12.00" maxIntervalHaltingDuration="12.00" intervalHaltingDurationSum="12.00" startedHalts="1.00" meanVehicleNumber="0.06" maxVehicleNumber="1" />
   <interval begin="2100.00" end="2400.00" id="e2_8" sampledSeconds="73.76" nVehEntered="8" nVehLeft="8" nVehSeen="8" meanSpeed="2.56" meanTimeLoss="7.40" meanOccupancy="4.99" maxOccupancy="43.00" meanMaxJamLengthInVehicles="0.14" meanMaxJamLengthInMeters="0.67" maxJamLengthInVehicles="2" maxJamLengthInMeters="10.12" jamLengthInVehiclesSum="42" jamLengthInMetersSum="201.64" meanHaltingDuration="11.50" maxHaltingDuration="17.00" haltingDurationSum="46.00" meanIntervalHaltingDuration="11.50" maxIntervalHaltingDuration="17.00" intervalHaltingDurationSum="46.00" startedHalts="4.00" meanVehicleNumber="0.27" maxVehicleNumber="2" />
   <interval begin="2400.00" end="2700.00" id="e2_8" sampledSeconds="155.37" nVehEntered="13" nVehLeft="13" nVehSeen="13" meanSpeed="2.03" meanTimeLoss="10.04" meanOccupancy="10.30" maxOccupancy="73.56" meanMaxJamLengthInVehicles="0.32" meanMaxJamLengthInMeters="1.60" maxJamLengthInVehicles="4" maxJamLengthInMeters="19.22" jamLengthInVehiclesSum="96" jamLengthInMetersSum="478.52" meanHaltingDuration="11.67" maxHaltingDuration="24.00" haltingDurationSum="105.00" meanIntervalHaltingDuration="11.67" maxIntervalHaltingDuration="24.00" intervalHaltingDurationSum="105.00" startedHalts="9.00" meanVehicleNumber="0.56" maxVehicleNumber="4" />
   <interval begin="2700.00" end="3000.00" id="e2_8" sampledSeconds="8.67" nVehEntered="3" nVehLeft="3" nVehSeen="3" meanSpeed="7.80" meanTimeLoss="1.30" meanOccupancy="0.57" maxOccupancy="21.50" meanMaxJamLengthInVehicles="0.00" meanMaxJamLengthInMeters="0.00" maxJamLengthInVehicles="0" maxJamLengthInMeters="0.00" jamLengthInVehiclesSum="0" jamLengthInMetersSum="0.00" meanHaltingDuration="0.00" maxHaltingDuration="0.00" haltingDurationSum="0.00" meanIntervalHaltingDuration="0.00" maxIntervalHaltingDuration="0.00" intervalHaltingDurationSum="0.00" startedHalts="1.00" meanVehicleNumber="0.04" maxVehicleNumber="1" />
   <interval begin="3000.00" end="3300.00" id="e2_8" sampledSeconds="98.29" nVehEntered="8" nVehLeft="8" nVehSeen="8" meanSpeed="1.87" meanTimeLoss="10.65" meanOccupancy="6.95" maxOccupancy="43.00" meanMaxJamLengthInVehicles="0.24" meanMaxJamLengthInMeters="1.15" maxJamLengthInVehicles="2" maxJamLengthInMeters="10.15" jamLengthInVehiclesSum="72" jamLengthInMetersSum="344.18" meanHaltingDuration="37.00" maxHaltingDuration="49.00" haltingDurationSum="74.00" meanIntervalHaltingDuration="37.00" maxIntervalHaltingDuration="49.00" intervalHaltingDurationSum="74.00" startedHalts="4.00" meanVehicleNumber="0.35" maxVehicleNumber="2" />
   <interval begin="3300.00" end="3600.00" id="e2_8" sampledSeconds="157.97" nVehEntered="10" nVehLeft="10" nVehSeen="10" meanSpeed="1.51" meanTimeLoss="13.97" meanOccupancy="10.35" maxOccupancy="73.58" meanMaxJamLengthInVehicles="0.37" meanMaxJamLengthInMeters="1.69" maxJamLengthInVehicles="4" maxJamLengthInMeters="19.22" jamLengthInVehiclesSum="110" jamLengthInMetersSum="507.76" meanHaltingDuration="19.33" maxHaltingDuration="50.00" haltingDurationSum="116.00" meanIntervalHaltingDuration="19.33" maxIntervalHaltingDuration="50.00" intervalHaltingDurationSum="116.00" startedHalts="6.00" meanVehicleNumber="0.57" maxVehicleNumber="4" />
</detector>
