<?xml version="1.0" encoding="UTF-8"?>

<!-- generated on 2023-09-16 21:06:09 by Eclipse SUMO GUI Version 1.18.0
<configuration xmlns:xsi="http://www.w3.org/2001/XMLSchema-instance" xsi:noNamespaceSchemaLocation="http://sumo.dlr.de/xsd/sumoConfiguration.xsd">

    <input>
        <net-file value="Multi_agent/nets/ingolstadt1/ingolstadt1.net.xml"/>
        <route-files value="Multi_agent/nets/ingolstadt1/ingolstadt1.rou.xml"/>
        <additional-files value="Multi_agent/nets/ingolstadt1/ingolstadt1.add.xml"/>
    </input>

    <processing>
        <time-to-teleport value="-1"/>
        <waiting-time-memory value="1000"/>
        <max-depart-delay value="-1"/>
    </processing>

    <traci_server>
        <remote-port value="51850"/>
    </traci_server>

    <random_number>
        <random value="true"/>
    </random_number>

    <gui_only>
        <quit-on-end value="true"/>
        <start value="true"/>
    </gui_only>

</configuration>
-->

<detector xmlns:xsi="http://www.w3.org/2001/XMLSchema-instance" xsi:noNamespaceSchemaLocation="http://sumo.dlr.de/xsd/det_e2_file.xsd">
   <interval begin="0.00" end="300.00" id="e2_0" sampledSeconds="46.72" nVehEntered="16" nVehLeft="16" nVehSeen="16" meanSpeed="8.27" meanTimeLoss="1.10" meanOccupancy="3.38" maxOccupancy="56.16" meanMaxJamLengthInVehicles="0.02" meanMaxJamLengthInMeters="0.08" maxJamLengthInVehicles="1" maxJamLengthInMeters="5.00" jamLengthInVehiclesSum="5" jamLengthInMetersSum="25.00" meanHaltingDuration="2.67" maxHaltingDuration="6.00" haltingDurationSum="8.00" meanIntervalHaltingDuration="2.67" maxIntervalHaltingDuration="6.00" intervalHaltingDurationSum="8.00" startedHalts="3.00" meanVehicleNumber="0.20" maxVehicleNumber="2" />
   <interval begin="300.00" end="600.00" id="e2_0" sampledSeconds="1.79" nVehEntered="1" nVehLeft="1" nVehSeen="1" meanSpeed="13.95" meanTimeLoss="0.08" meanOccupancy="0.13" maxOccupancy="25.00" meanMaxJamLengthInVehicles="0.00" meanMaxJamLengthInMeters="0.00" maxJamLengthInVehicles="0" maxJamLengthInMeters="0.00" jamLengthInVehiclesSum="0" jamLengthInMetersSum="0.00" meanHaltingDuration="0.00" maxHaltingDuration="0.00" haltingDurationSum="0.00" meanIntervalHaltingDuration="0.00" maxIntervalHaltingDuration="0.00" intervalHaltingDurationSum="0.00" startedHalts="0.00" meanVehicleNumber="0.01" maxVehicleNumber="1" />
   <interval begin="600.00" end="900.00" id="e2_0" sampledSeconds="247.06" nVehEntered="47" nVehLeft="47" nVehSeen="47" meanSpeed="4.09" meanTimeLoss="3.66" meanOccupancy="18.72" maxOccupancy="70.28" meanMaxJamLengthInVehicles="0.27" meanMaxJamLengthInMeters="1.47" maxJamLengthInVehicles="2" maxJamLengthInMeters="12.58" jamLengthInVehiclesSum="81" jamLengthInMetersSum="442.16" meanHaltingDuration="5.26" maxHaltingDuration="10.00" haltingDurationSum="100.00" meanIntervalHaltingDuration="5.26" maxIntervalHaltingDuration="10.00" intervalHaltingDurationSum="100.00" startedHalts="19.00" meanVehicleNumber="0.96" maxVehicleNumber="3" />
   <interval begin="900.00" end="1200.00" id="e2_0" sampledSeconds="50.59" nVehEntered="12" nVehLeft="12" nVehSeen="12" meanSpeed="5.49" meanTimeLoss="2.54" meanOccupancy="3.83" maxOccupancy="50.00" meanMaxJamLengthInVehicles="0.05" meanMaxJamLengthInMeters="0.23" maxJamLengthInVehicles="1" maxJamLengthInMeters="5.00" jamLengthInVehiclesSum="14" jamLengthInMetersSum="70.00" meanHaltingDuration="4.50" maxHaltingDuration="9.00" haltingDurationSum="18.00" meanIntervalHaltingDuration="4.50" maxIntervalHaltingDuration="9.00" intervalHaltingDurationSum="18.00" startedHalts="4.00" meanVehicleNumber="0.21" maxVehicleNumber="2" />
   <interval begin="1200.00" end="1500.00" id="e2_0" sampledSeconds="185.19" nVehEntered="35" nVehLeft="35" nVehSeen="35" meanSpeed="4.03" meanTimeLoss="3.71" meanOccupancy="14.00" maxOccupancy="61.41" meanMaxJamLengthInVehicles="0.22" meanMaxJamLengthInMeters="1.16" maxJamLengthInVehicles="2" maxJamLengthInMeters="12.62" jamLengthInVehiclesSum="66" jamLengthInMetersSum="347.75" meanHaltingDuration="6.08" maxHaltingDuration="16.00" haltingDurationSum="79.00" meanIntervalHaltingDuration="6.08" maxIntervalHaltingDuration="16.00" intervalHaltingDurationSum="79.00" startedHalts="13.00" meanVehicleNumber="0.73" maxVehicleNumber="3" />
   <interval begin="1500.00" end="1800.00" id="e2_0" sampledSeconds="27.07" nVehEntered="7" nVehLeft="7" nVehSeen="7" meanSpeed="6.47" meanTimeLoss="1.98" meanOccupancy="1.91" maxOccupancy="25.00" meanMaxJamLengthInVehicles="0.02" meanMaxJamLengthInMeters="0.10" maxJamLengthInVehicles="1" maxJamLengthInMeters="5.00" jamLengthInVehiclesSum="6" jamLengthInMetersSum="30.00" meanHaltingDuration="4.00" maxHaltingDuration="7.00" haltingDurationSum="8.00" meanIntervalHaltingDuration="4.00" maxIntervalHaltingDuration="7.00" intervalHaltingDurationSum="8.00" startedHalts="2.00" meanVehicleNumber="0.11" maxVehicleNumber="2" />
   <interval begin="1800.00" end="2100.00" id="e2_0" sampledSeconds="138.21" nVehEntered="34" nVehLeft="34" nVehSeen="34" meanSpeed="5.81" meanTimeLoss="2.32" meanOccupancy="10.31" maxOccupancy="50.00" meanMaxJamLengthInVehicles="0.15" meanMaxJamLengthInMeters="0.81" maxJamLengthInVehicles="2" maxJamLengthInMeters="12.65" jamLengthInVehiclesSum="44" jamLengthInMetersSum="242.94" meanHaltingDuration="7.29" maxHaltingDuration="9.00" haltingDurationSum="51.00" meanIntervalHaltingDuration="7.29" maxIntervalHaltingDuration="9.00" intervalHaltingDurationSum="51.00" startedHalts="7.00" meanVehicleNumber="0.56" maxVehicleNumber="3" />
   <interval begin="2100.00" end="2400.00" id="e2_0" sampledSeconds="87.93" nVehEntered="28" nVehLeft="27" nVehSeen="28" meanSpeed="6.58" meanTimeLoss="1.60" meanOccupancy="6.50" maxOccupancy="66.96" meanMaxJamLengthInVehicles="0.07" meanMaxJamLengthInMeters="0.38" maxJamLengthInVehicles="2" maxJamLengthInMeters="12.52" jamLengthInVehiclesSum="21" jamLengthInMetersSum="112.52" meanHaltingDuration="4.50" maxHaltingDuration="9.00" haltingDurationSum="27.00" meanIntervalHaltingDuration="4.50" maxIntervalHaltingDuration="9.00" intervalHaltingDurationSum="27.00" startedHalts="6.00" meanVehicleNumber="0.39" maxVehicleNumber="3" />
   <interval begin="2400.00" end="2700.00" id="e2_0" sampledSeconds="263.56" nVehEntered="52" nVehLeft="53" nVehSeen="53" meanSpeed="4.79" meanTimeLoss="3.24" meanOccupancy="19.58" maxOccupancy="62.61" meanMaxJamLengthInVehicles="0.29" meanMaxJamLengthInMeters="1.50" maxJamLengthInVehicles="2" maxJamLengthInMeters="12.51" jamLengthInVehiclesSum="86" jamLengthInMetersSum="450.05" meanHaltingDuration="5.78" maxHaltingDuration="10.00" haltingDurationSum="104.00" meanIntervalHaltingDuration="5.78" maxIntervalHaltingDuration="10.00" intervalHaltingDurationSum="104.00" startedHalts="18.00" meanVehicleNumber="1.03" maxVehicleNumber="3" />
   <interval begin="2700.00" end="3000.00" id="e2_0" sampledSeconds="24.60" nVehEntered="9" nVehLeft="9" nVehSeen="9" meanSpeed="9.15" meanTimeLoss="0.94" meanOccupancy="1.74" maxOccupancy="25.00" meanMaxJamLengthInVehicles="0.00" meanMaxJamLengthInMeters="0.02" maxJamLengthInVehicles="1" maxJamLengthInMeters="5.00" jamLengthInVehiclesSum="1" jamLengthInMetersSum="5.00" meanHaltingDuration="2.00" maxHaltingDuration="2.00" haltingDurationSum="2.00" meanIntervalHaltingDuration="2.00" maxIntervalHaltingDuration="2.00" intervalHaltingDurationSum="2.00" startedHalts="1.00" meanVehicleNumber="0.11" maxVehicleNumber="2" />
   <interval begin="3000.00" end="3300.00" id="e2_0" sampledSeconds="197.12" nVehEntered="47" nVehLeft="47" nVehSeen="47" meanSpeed="4.95" meanTimeLoss="2.65" meanOccupancy="14.97" maxOccupancy="60.00" meanMaxJamLengthInVehicles="0.20" meanMaxJamLengthInMeters="1.06" maxJamLengthInVehicles="2" maxJamLengthInMeters="13.06" jamLengthInVehiclesSum="61" jamLengthInMetersSum="318.27" meanHaltingDuration="6.08" maxHaltingDuration="10.00" haltingDurationSum="73.00" meanIntervalHaltingDuration="6.08" maxIntervalHaltingDuration="10.00" intervalHaltingDurationSum="73.00" startedHalts="12.00" meanVehicleNumber="0.82" maxVehicleNumber="3" />
   <interval begin="3300.00" end="3600.00" id="e2_0" sampledSeconds="7.44" nVehEntered="4" nVehLeft="4" nVehSeen="4" meanSpeed="13.44" meanTimeLoss="0.12" meanOccupancy="0.53" maxOccupancy="25.00" meanMaxJamLengthInVehicles="0.00" meanMaxJamLengthInMeters="0.00" maxJamLengthInVehicles="0" maxJamLengthInMeters="0.00" jamLengthInVehiclesSum="0" jamLengthInMetersSum="0.00" meanHaltingDuration="0.00" maxHaltingDuration="0.00" haltingDurationSum="0.00" meanIntervalHaltingDuration="0.00" maxIntervalHaltingDuration="0.00" intervalHaltingDurationSum="0.00" startedHalts="0.00" meanVehicleNumber="0.04" maxVehicleNumber="1" />
</detector>
